{"aWVSSx-y3": {"intIntoBuffFW": 30.0, "ScientificName": "Gyrinophilus subterraneus", "ysnHydroWV": false, "intAuxBuff": null, "strForIntBuffer": null, "ysnHandModel": false, "intIntoBuffOW": null, "Season": "y", "intElevMax": null, "PrimEcoSys": ["Appalachian Hemlock-Hardwood Forest", "Appalachian Shale Barrens", "Central Appalachian Alkaline Glade and Woodland", "Central Appalachian Oak and Pine Forest", "Central Appalachian Pine-Oak Rocky Woodland", "Central Interior and Appalachian Riparian Systems", "Northeastern Interior Dry-Mesic Oak Forest", "Open Water (Fresh)", "South-Central Interior Mesophytic Forest", "Southern Ridge and Valley Dry Calcareous Forest", "Southern and Central Appalachian Cove Forest"], "AuxEcoSys": [], "SpeciesCode": "aWVSSx", "intIntoBuffWV": null, "cbxContPatch": false, "SubspeciesName": "", "intFromBuffFW": 30.0, "intElevMin": null, "ysnHydroOW": false, "Region": "Northeast", "CommonName": "West Virginia Spring Salamander", "ysnUrbanInclude": false, "strUseForInt": null, "intEdgeEcoWidth": null, "intFromBuffWV": null, "strStreamVel": null, "strSalinity": "Freshwater Only", "strEdgeType": null, "ysnHydroFW": true, "intContPatchSize": null, "ysnUrbanExclude": false, "strAvoid": null, "intFromBuffOW": null}, "data_layers": {"Land Cover": "https://doi.org/10.5066/F7959GF5", "Hydrography": "https://doi.org/10.5066/F7959GF5", "Elevation": "https://doi.org/10.5066/F7959GF5", "ForeEdge": "https://doi.org/10.5066/F7959GF5"}}