{"doi": "???????", "input_layers": {"intEdgeEcoWidth": "https://doi.org/10.5066/????????", "strAvoid": "https://doi.org/10.5066/????????", "ysnHydroWV": "https://doi.org/10.5066/????????", "strForIntBuffer": "https://doi.org/10.5066/????????", "intFromBuffFW": "https://doi.org/10.5066/????????", "intIntoBuffOW": "https://doi.org/10.5066/????????", "intElevMax": "https://doi.org/10.5066/????????", "PrimEcoSys": "https://doi.org/10.5066/????????", "AuxEcoSys": "https://doi.org/10.5066/????????", "intIntoBuffWV": "https://doi.org/10.5066/????????", "ysnUrbanExclude": "https://doi.org/10.5066/????????", "intElevMin": "https://doi.org/10.5066/????????", "Region": "https://doi.org/10.5066/????????", "ysnHydroOW": "https://doi.org/10.5066/????????", "ysnUrbanInclude": "https://doi.org/10.5066/????????", "strUseForInt": "https://doi.org/10.5066/????????", "intFromBuffWV": "https://doi.org/10.5066/????????", "strStreamVel": "https://doi.org/10.5066/????????", "strEdgeType": "https://doi.org/10.5066/????????", "strSalinity": "https://doi.org/10.5066/????????", "ysnHydroFW": "https://doi.org/10.5066/????????", "intFromBuffOW": "https://doi.org/10.5066/????????"}, "models": {"bRTBEx-w5": {"intIntoBuffFW": null, "ScientificName": "Pachyramphus aglaiae", "ysnHydroWV": false, "intAuxBuff": null, "strForIntBuffer": null, "intContPatchSize": null, "ysnHandModel": false, "intIntoBuffOW": null, "Season": "w", "intElevMax": 100, "PrimEcoSys": [[4141, "East-Central Texas Plains Riparian Forest"], [8406, "Introduced Riparian and Wetland Vegetation"], [9833, "North American Warm Desert Lower Montane Riparian Woodland and Shrubland"], [9856, "North American Warm Desert Riparian Systems"], [9835, "North American Warm Desert Riparian Woodland and Shrubland"], [5217, "Tamaulipan Calcareous Thornscrub"], [5216, "Tamaulipan Mesquite Upland Scrub"]], "AuxEcoSys": [], "SpeciesCode": "bRTBEx", "intIntoBuffWV": null, "cbxContPatch": false, "SubspeciesName": "", "intFromBuffFW": null, "memHandModelNotes": null, "intElevMin": 105, "ysnHydroOW": false, "Region": "Great Plains", "CommonName": "Rose-throated Becard", "ysnUrbanInclude": false, "strUseForInt": null, "intEdgeEcoWidth": null, "intFromBuffWV": null, "strStreamVel": null, "Modeler": "", "strEdgeType": null, "strSalinity": null, "ysnHydroFW": false, "Reviewer": "", "ysnUrbanExclude": false, "strAvoid": null, "intFromBuffOW": null}, "bRTBEx-s4": {"intIntoBuffFW": null, "ScientificName": "Pachyramphus aglaiae", "ysnHydroWV": false, "intAuxBuff": null, "strForIntBuffer": null, "intContPatchSize": null, "ysnHandModel": false, "intIntoBuffOW": null, "Season": "s", "intElevMax": 100, "PrimEcoSys": [[8406, "Introduced Riparian and Wetland Vegetation"], [9833, "North American Warm Desert Lower Montane Riparian Woodland and Shrubland"], [9834, "North American Warm Desert Riparian Mesquite Bosque"], [9856, "North American Warm Desert Riparian Systems"], [9835, "North American Warm Desert Riparian Woodland and Shrubland"], [8504, "Ruderal Wetland"], [5207, "Sonora-Mojave Creosotebush-White Bursage Desert Scrub"], [5208, "Sonora-Mojave Mixed Salt Desert Scrub"], [5409, "Sonora-Mojave Semi-Desert Chaparral"], [5209, "Sonoran Mid-Elevation Desert Scrub"], [5213, "Sonoran Paloverde-Mixed Cacti Desert Scrub"]], "AuxEcoSys": [], "SpeciesCode": "bRTBEx", "intIntoBuffWV": null, "cbxContPatch": false, "SubspeciesName": "", "intFromBuffFW": null, "memHandModelNotes": null, "intElevMin": 105, "ysnHydroOW": false, "Region": "Southwest", "CommonName": "Rose-throated Becard", "ysnUrbanInclude": false, "strUseForInt": null, "intEdgeEcoWidth": null, "intFromBuffWV": null, "strStreamVel": null, "Modeler": "", "strEdgeType": null, "strSalinity": null, "ysnHydroFW": false, "Reviewer": "", "ysnUrbanExclude": false, "strAvoid": null, "intFromBuffOW": null}}, "references": {"B95HOW01USGP": "Howell, S. N. G. and S. Webb. 1995. A guide to the birds of Mexico and Northern Central America. Oxford Univ. Press, New York."}, "habitat_description": null, "taxonomic": {"gap_code": "bRTBEx", "ELCode": "ABPAE53070", "scientific_name": "Pachyramphus aglaiae", "ITIS_TSN": "178384", "Global_SEQ_ID": "100681", "common_name": "Rose-throated Becard"}}