{"doi": "???????", "input_layers": {"intEdgeEcoWidth": "https://doi.org/10.5066/????????", "strAvoid": "https://doi.org/10.5066/????????", "ysnHydroWV": "https://doi.org/10.5066/????????", "strForIntBuffer": "https://doi.org/10.5066/????????", "intFromBuffFW": "https://doi.org/10.5066/????????", "intIntoBuffOW": "https://doi.org/10.5066/????????", "intElevMax": "https://doi.org/10.5066/????????", "PrimEcoSys": "https://doi.org/10.5066/????????", "AuxEcoSys": "https://doi.org/10.5066/????????", "intIntoBuffWV": "https://doi.org/10.5066/????????", "ysnUrbanExclude": "https://doi.org/10.5066/????????", "intElevMin": "https://doi.org/10.5066/????????", "Region": "https://doi.org/10.5066/????????", "ysnHydroOW": "https://doi.org/10.5066/????????", "ysnUrbanInclude": "https://doi.org/10.5066/????????", "strUseForInt": "https://doi.org/10.5066/????????", "intFromBuffWV": "https://doi.org/10.5066/????????", "strStreamVel": "https://doi.org/10.5066/????????", "strEdgeType": "https://doi.org/10.5066/????????", "strSalinity": "https://doi.org/10.5066/????????", "ysnHydroFW": "https://doi.org/10.5066/????????", "intFromBuffOW": "https://doi.org/10.5066/????????"}, "models": {"bYHBLx-w4": {"intIntoBuffFW": null, "ScientificName": "Xanthocephalus xanthocephalus", "ysnHydroWV": false, "intAuxBuff": null, "strForIntBuffer": null, "intContPatchSize": null, "ysnHandModel": false, "intIntoBuffOW": null, "Season": "w", "intElevMax": 100, "PrimEcoSys": [[1402, "Cultivated Cropland"], [1201, "Developed, Open Space"], [8103, "Disturbed/Successional - Grass/Forb Regeneration"], [8108, "Harvested Forest - Grass/Forb Regeneration"], [9403, "Inter-Mountain Basins Interdunal Swale Wetland"], [8404, "Introduced Upland Vegetation - Annual Grassland"], [8403, "Introduced Upland Vegetation - Forbland"], [8405, "Introduced Upland Vegetation - Perennial Grassland"], [8407, "Introduced Upland Vegetation - Perennial Grassland and Forbland"], [9504, "Mediterranean California Subalpine-Montane Fen"], [9227, "North American Arid West Emergent Marsh"], [1403, "Pasture/Hay"], [8301, "Recently Burned"], [8302, "Recently Burned Forest"], [8303, "Recently Burned Grassland"], [8101, "Recently Logged Areas"], [9606, "Rocky Mountain Alpine-Montane Wet Meadow"], [9503, "Rocky Mountain Subalpine-Montane Fen"], [8503, "Ruderal Upland - Old Field"], [9816, "Tamaulipan Floodplain"], [9228, "Temperate Pacific Freshwater Emergent Marsh"], [9608, "Temperate Pacific Montane Wet Meadow"], [8104, "Utility Swath - Herbaceous"], [9710, "Western Great Plains Closed Depression Wetland"], [9706, "Western Great Plains Depressional Wetland Systems"], [9823, "Western Great Plains Floodplain"], [9814, "Western Great Plains Floodplain Systems"], [9707, "Western Great Plains Open Freshwater Depression Wetland"], [9711, "Western Great Plains Saline Depression Wetland"]], "AuxEcoSys": [], "SpeciesCode": "bYHBLx", "intIntoBuffWV": null, "cbxContPatch": false, "SubspeciesName": "", "intFromBuffFW": null, "memHandModelNotes": null, "intElevMin": 105, "ysnHydroOW": false, "Region": "Southwest", "CommonName": "Yellow-headed Blackbird", "ysnUrbanInclude": false, "strUseForInt": null, "intEdgeEcoWidth": null, "intFromBuffWV": null, "strStreamVel": null, "Modeler": "", "strEdgeType": null, "strSalinity": null, "ysnHydroFW": false, "Reviewer": "", "ysnUrbanExclude": false, "strAvoid": null, "intFromBuffOW": null}, "bYHBLx-w5": {"intIntoBuffFW": null, "ScientificName": "Xanthocephalus xanthocephalus", "ysnHydroWV": false, "intAuxBuff": null, "strForIntBuffer": null, "intContPatchSize": null, "ysnHandModel": false, "intIntoBuffOW": null, "Season": "w", "intElevMax": 100, "PrimEcoSys": [[1402, "Cultivated Cropland"], [1202, "Developed, Low Intensity"], [1201, "Developed, Open Space"], [8103, "Disturbed/Successional - Grass/Forb Regeneration"], [8108, "Harvested Forest - Grass/Forb Regeneration"], [9403, "Inter-Mountain Basins Interdunal Swale Wetland"], [8404, "Introduced Upland Vegetation - Annual Grassland"], [8403, "Introduced Upland Vegetation - Forbland"], [8405, "Introduced Upland Vegetation - Perennial Grassland"], [8407, "Introduced Upland Vegetation - Perennial Grassland and Forbland"], [9227, "North American Arid West Emergent Marsh"], [1403, "Pasture/Hay"], [8301, "Recently Burned"], [8302, "Recently Burned Forest"], [8303, "Recently Burned Grassland"], [8101, "Recently Logged Areas"], [9606, "Rocky Mountain Alpine-Montane Wet Meadow"], [9503, "Rocky Mountain Subalpine-Montane Fen"], [8503, "Ruderal Upland - Old Field"], [9816, "Tamaulipan Floodplain"], [9853, "Texas-Louisiana Coastal Prairie Slough"], [8104, "Utility Swath - Herbaceous"], [9710, "Western Great Plains Closed Depression Wetland"], [9706, "Western Great Plains Depressional Wetland Systems"], [9823, "Western Great Plains Floodplain"], [9814, "Western Great Plains Floodplain Systems"], [9707, "Western Great Plains Open Freshwater Depression Wetland"], [9711, "Western Great Plains Saline Depression Wetland"]], "AuxEcoSys": [], "SpeciesCode": "bYHBLx", "intIntoBuffWV": null, "cbxContPatch": false, "SubspeciesName": "", "intFromBuffFW": null, "memHandModelNotes": null, "intElevMin": 105, "ysnHydroOW": false, "Region": "Great Plains", "CommonName": "Yellow-headed Blackbird", "ysnUrbanInclude": false, "strUseForInt": null, "intEdgeEcoWidth": null, "intFromBuffWV": null, "strStreamVel": null, "Modeler": "", "strEdgeType": null, "strSalinity": null, "ysnHydroFW": false, "Reviewer": "", "ysnUrbanExclude": false, "strAvoid": null, "intFromBuffOW": null}, "bYHBLx-s2": {"intIntoBuffFW": null, "ScientificName": "Xanthocephalus xanthocephalus", "ysnHydroWV": false, "intAuxBuff": 250.0, "strForIntBuffer": null, "intContPatchSize": null, "ysnHandModel": false, "intIntoBuffOW": null, "Season": "s", "intElevMax": 100, "PrimEcoSys": [[9605, "Eastern Great Plains Wet Meadow, Prairie, and Marsh"], [9221, "Great Lakes Coastal Marsh Systems"], [9229, "Great Lakes Freshwater Estuary and Delta"], [9705, "Great Plains Prairie Pothole"], [9242, "Laurentian-Acadian Freshwater Marsh"], [9234, "Northern Great Lakes Coastal Marsh"], [9826, "Northwestern Great Plains Floodplain"], [9706, "Western Great Plains Depressional Wetland Systems"]], "AuxEcoSys": [[7302, "Central Mixedgrass Prairie"], [7315, "Central Tallgrass Prairie"], [1402, "Cultivated Cropland"], [8103, "Disturbed/Successional - Grass/Forb Regeneration"], [4131, "Eastern Great Plains Tallgrass Aspen Parkland"], [7402, "Great Lakes Wet-Mesic Lakeplain Prairie"], [8108, "Harvested Forest - Grass/Forb Regeneration"], [8404, "Introduced Upland Vegetation - Annual Grassland"], [8403, "Introduced Upland Vegetation - Forbland"], [8405, "Introduced Upland Vegetation - Perennial Grassland"], [8407, "Introduced Upland Vegetation - Perennial Grassland and Forbland"], [8408, "Modified/Managed Southern Tall Grassland"], [7312, "North-Central Interior Sand and Gravel Tallgrass Prairie"], [7314, "Northern Tallgrass Prairie"], [7306, "Northwestern Great Plains Mixedgrass Prairie"], [1403, "Pasture/Hay"], [8301, "Recently Burned"], [8302, "Recently Burned Forest"], [8303, "Recently Burned Grassland"], [8101, "Recently Logged Areas"], [8503, "Ruderal Upland - Old Field"], [7317, "Southeastern Great Plains Tallgrass Prairie"], [8104, "Utility Swath - Herbaceous"], [7319, "West Gulf Coastal Plain Northern Calcareous Prairie"], [7320, "West Gulf Coastal Plain Southern Calcareous Prairie"], [7309, "Western Great Plains Sand Prairie"], [7310, "Western Great Plains Shortgrass Prairie"], [7311, "Western Great Plains Tallgrass Prairie"]], "SpeciesCode": "bYHBLx", "intIntoBuffWV": null, "cbxContPatch": false, "SubspeciesName": "", "intFromBuffFW": null, "memHandModelNotes": null, "intElevMin": 105, "ysnHydroOW": false, "Region": "Upper Midwest", "CommonName": "Yellow-headed Blackbird", "ysnUrbanInclude": false, "strUseForInt": null, "intEdgeEcoWidth": null, "intFromBuffWV": null, "strStreamVel": null, "Modeler": "", "strEdgeType": null, "strSalinity": null, "ysnHydroFW": false, "Reviewer": "", "ysnUrbanExclude": false, "strAvoid": null, "intFromBuffOW": null}, "bYHBLx-s3": {"intIntoBuffFW": null, "ScientificName": "Xanthocephalus xanthocephalus", "ysnHydroWV": false, "intAuxBuff": 250.0, "strForIntBuffer": null, "intContPatchSize": null, "ysnHandModel": false, "intIntoBuffOW": null, "Season": "s", "intElevMax": 100, "PrimEcoSys": [[9605, "Eastern Great Plains Wet Meadow, Prairie, and Marsh"], [9221, "Great Lakes Coastal Marsh Systems"], [9229, "Great Lakes Freshwater Estuary and Delta"], [9705, "Great Plains Prairie Pothole"], [9242, "Laurentian-Acadian Freshwater Marsh"], [9234, "Northern Great Lakes Coastal Marsh"], [9826, "Northwestern Great Plains Floodplain"], [9706, "Western Great Plains Depressional Wetland Systems"]], "AuxEcoSys": [[7302, "Central Mixedgrass Prairie"], [7315, "Central Tallgrass Prairie"], [1402, "Cultivated Cropland"], [8103, "Disturbed/Successional - Grass/Forb Regeneration"], [4131, "Eastern Great Plains Tallgrass Aspen Parkland"], [7402, "Great Lakes Wet-Mesic Lakeplain Prairie"], [8108, "Harvested Forest - Grass/Forb Regeneration"], [8404, "Introduced Upland Vegetation - Annual Grassland"], [8403, "Introduced Upland Vegetation - Forbland"], [8405, "Introduced Upland Vegetation - Perennial Grassland"], [8407, "Introduced Upland Vegetation - Perennial Grassland and Forbland"], [8408, "Modified/Managed Southern Tall Grassland"], [7312, "North-Central Interior Sand and Gravel Tallgrass Prairie"], [7314, "Northern Tallgrass Prairie"], [7306, "Northwestern Great Plains Mixedgrass Prairie"], [1403, "Pasture/Hay"], [8301, "Recently Burned"], [8302, "Recently Burned Forest"], [8303, "Recently Burned Grassland"], [8101, "Recently Logged Areas"], [8503, "Ruderal Upland - Old Field"], [7317, "Southeastern Great Plains Tallgrass Prairie"], [8104, "Utility Swath - Herbaceous"], [7319, "West Gulf Coastal Plain Northern Calcareous Prairie"], [7320, "West Gulf Coastal Plain Southern Calcareous Prairie"], [7309, "Western Great Plains Sand Prairie"], [7310, "Western Great Plains Shortgrass Prairie"], [7311, "Western Great Plains Tallgrass Prairie"]], "SpeciesCode": "bYHBLx", "intIntoBuffWV": null, "cbxContPatch": false, "SubspeciesName": "", "intFromBuffFW": null, "memHandModelNotes": null, "intElevMin": 105, "ysnHydroOW": false, "Region": "Northeast", "CommonName": "Yellow-headed Blackbird", "ysnUrbanInclude": false, "strUseForInt": null, "intEdgeEcoWidth": null, "intFromBuffWV": null, "strStreamVel": null, "Modeler": "", "strEdgeType": null, "strSalinity": null, "ysnHydroFW": false, "Reviewer": "", "ysnUrbanExclude": false, "strAvoid": null, "intFromBuffOW": null}, "bYHBLx-s1": {"intIntoBuffFW": null, "ScientificName": "Xanthocephalus xanthocephalus", "ysnHydroWV": false, "intAuxBuff": 250.0, "strForIntBuffer": null, "intContPatchSize": null, "ysnHandModel": false, "intIntoBuffOW": null, "Season": "s", "intElevMax": 100, "PrimEcoSys": [[1201, "Developed, Open Space"], [9403, "Inter-Mountain Basins Interdunal Swale Wetland"], [9505, "Mediterranean California Serpentine Fen"], [9504, "Mediterranean California Subalpine-Montane Fen"], [9227, "North American Arid West Emergent Marsh"], [9502, "North Pacific Bog and Fen"], [9226, "North Pacific Intertidal Freshwater Wetland"], [9228, "Temperate Pacific Freshwater Emergent Marsh"]], "AuxEcoSys": [[7501, "California Central Valley and Southern Coastal Grassland"], [7401, "California Mesic Serpentine Grassland"], [7502, "California Northern Coastal Grassland"], [1402, "Cultivated Cropland"], [8103, "Disturbed/Successional - Grass/Forb Regeneration"], [8108, "Harvested Forest - Grass/Forb Regeneration"], [8106, "Harvested Forest - Northwestern Conifer Regeneration"], [7305, "Inter-Mountain Basins Semi-Desert Grassland"], [8404, "Introduced Upland Vegetation - Annual Grassland"], [8403, "Introduced Upland Vegetation - Forbland"], [8405, "Introduced Upland Vegetation - Perennial Grassland"], [8407, "Introduced Upland Vegetation - Perennial Grassland and Forbland"], [7101, "Mediterranean California Alpine Dry Tundra"], [7201, "Mediterranean California Subalpine Meadow"], [7104, "North Pacific Alpine and Subalpine Dry Grassland"], [7202, "North Pacific Montane Grassland"], [1403, "Pasture/Hay"], [8301, "Recently Burned"], [8302, "Recently Burned Forest"], [8303, "Recently Burned Grassland"], [8101, "Recently Logged Areas"], [8503, "Ruderal Upland - Old Field"], [9608, "Temperate Pacific Montane Wet Meadow"], [8104, "Utility Swath - Herbaceous"]], "SpeciesCode": "bYHBLx", "intIntoBuffWV": null, "cbxContPatch": false, "SubspeciesName": "", "intFromBuffFW": null, "memHandModelNotes": null, "intElevMin": 105, "ysnHydroOW": false, "Region": "Northwest", "CommonName": "Yellow-headed Blackbird", "ysnUrbanInclude": false, "strUseForInt": null, "intEdgeEcoWidth": null, "intFromBuffWV": null, "strStreamVel": null, "Modeler": "", "strEdgeType": null, "strSalinity": null, "ysnHydroFW": false, "Reviewer": "", "ysnUrbanExclude": false, "strAvoid": null, "intFromBuffOW": null}, "bYHBLx-s4": {"intIntoBuffFW": null, "ScientificName": "Xanthocephalus xanthocephalus", "ysnHydroWV": false, "intAuxBuff": 250.0, "strForIntBuffer": null, "intContPatchSize": null, "ysnHandModel": false, "intIntoBuffOW": null, "Season": "s", "intElevMax": 100, "PrimEcoSys": [[9504, "Mediterranean California Subalpine-Montane Fen"], [9227, "North American Arid West Emergent Marsh"], [9503, "Rocky Mountain Subalpine-Montane Fen"], [9228, "Temperate Pacific Freshwater Emergent Marsh"], [9710, "Western Great Plains Closed Depression Wetland"], [9706, "Western Great Plains Depressional Wetland Systems"], [9823, "Western Great Plains Floodplain"], [9814, "Western Great Plains Floodplain Systems"], [9707, "Western Great Plains Open Freshwater Depression Wetland"]], "AuxEcoSys": [[7501, "California Central Valley and Southern Coastal Grassland"], [7401, "California Mesic Serpentine Grassland"], [7502, "California Northern Coastal Grassland"], [7302, "Central Mixedgrass Prairie"], [7304, "Columbia Basin Foothill and Canyon Dry Grassland"], [5305, "Columbia Plateau Steppe and Grassland"], [1402, "Cultivated Cropland"], [8103, "Disturbed/Successional - Grass/Forb Regeneration"], [8108, "Harvested Forest - Grass/Forb Regeneration"], [7305, "Inter-Mountain Basins Semi-Desert Grassland"], [8404, "Introduced Upland Vegetation - Annual Grassland"], [8403, "Introduced Upland Vegetation - Forbland"], [8405, "Introduced Upland Vegetation - Perennial Grassland"], [8407, "Introduced Upland Vegetation - Perennial Grassland and Forbland"], [7101, "Mediterranean California Alpine Dry Tundra"], [7201, "Mediterranean California Subalpine Meadow"], [8408, "Modified/Managed Southern Tall Grassland"], [7202, "North Pacific Montane Grassland"], [7203, "Northern Rocky Mountain Lower Montane, Foothill and Valley Grassland"], [7204, "Northern Rocky Mountain Subalpine-Upper Montane Grassland"], [7306, "Northwestern Great Plains Mixedgrass Prairie"], [1403, "Pasture/Hay"], [8301, "Recently Burned"], [8302, "Recently Burned Forest"], [8303, "Recently Burned Grassland"], [8101, "Recently Logged Areas"], [9606, "Rocky Mountain Alpine-Montane Wet Meadow"], [7103, "Rocky Mountain Dry Tundra"], [7205, "Rocky Mountain Subalpine-Montane Mesic Meadow"], [8503, "Ruderal Upland - Old Field"], [7206, "Southern Rocky Mountain Montane-Subalpine Grassland"], [9608, "Temperate Pacific Montane Wet Meadow"], [8104, "Utility Swath - Herbaceous"], [7308, "Western Great Plains Foothill and Piedmont Grassland"], [7310, "Western Great Plains Shortgrass Prairie"]], "SpeciesCode": "bYHBLx", "intIntoBuffWV": null, "cbxContPatch": false, "SubspeciesName": "", "intFromBuffFW": null, "memHandModelNotes": null, "intElevMin": 105, "ysnHydroOW": false, "Region": "Southwest", "CommonName": "Yellow-headed Blackbird", "ysnUrbanInclude": false, "strUseForInt": null, "intEdgeEcoWidth": null, "intFromBuffWV": null, "strStreamVel": null, "Modeler": "", "strEdgeType": null, "strSalinity": null, "ysnHydroFW": false, "Reviewer": "", "ysnUrbanExclude": false, "strAvoid": null, "intFromBuffOW": null}, "bYHBLx-s5": {"intIntoBuffFW": null, "ScientificName": "Xanthocephalus xanthocephalus", "ysnHydroWV": false, "intAuxBuff": 250.0, "strForIntBuffer": null, "intContPatchSize": null, "ysnHandModel": false, "intIntoBuffOW": null, "Season": "s", "intElevMax": 100, "PrimEcoSys": [[9605, "Eastern Great Plains Wet Meadow, Prairie, and Marsh"], [9705, "Great Plains Prairie Pothole"], [9227, "North American Arid West Emergent Marsh"], [9826, "Northwestern Great Plains Floodplain"], [9503, "Rocky Mountain Subalpine-Montane Fen"], [9710, "Western Great Plains Closed Depression Wetland"], [9706, "Western Great Plains Depressional Wetland Systems"], [9823, "Western Great Plains Floodplain"], [9707, "Western Great Plains Open Freshwater Depression Wetland"]], "AuxEcoSys": [[7302, "Central Mixedgrass Prairie"], [7315, "Central Tallgrass Prairie"], [1402, "Cultivated Cropland"], [8103, "Disturbed/Successional - Grass/Forb Regeneration"], [4131, "Eastern Great Plains Tallgrass Aspen Parkland"], [8108, "Harvested Forest - Grass/Forb Regeneration"], [7305, "Inter-Mountain Basins Semi-Desert Grassland"], [8404, "Introduced Upland Vegetation - Annual Grassland"], [8403, "Introduced Upland Vegetation - Forbland"], [8405, "Introduced Upland Vegetation - Perennial Grassland"], [8407, "Introduced Upland Vegetation - Perennial Grassland and Forbland"], [8408, "Modified/Managed Southern Tall Grassland"], [7312, "North-Central Interior Sand and Gravel Tallgrass Prairie"], [7203, "Northern Rocky Mountain Lower Montane, Foothill and Valley Grassland"], [7204, "Northern Rocky Mountain Subalpine-Upper Montane Grassland"], [7306, "Northwestern Great Plains Mixedgrass Prairie"], [1403, "Pasture/Hay"], [8301, "Recently Burned"], [8302, "Recently Burned Forest"], [8303, "Recently Burned Grassland"], [8101, "Recently Logged Areas"], [9606, "Rocky Mountain Alpine-Montane Wet Meadow"], [7103, "Rocky Mountain Dry Tundra"], [7205, "Rocky Mountain Subalpine-Montane Mesic Meadow"], [8503, "Ruderal Upland - Old Field"], [7317, "Southeastern Great Plains Tallgrass Prairie"], [7316, "Southern Blackland Tallgrass Prairie"], [7206, "Southern Rocky Mountain Montane-Subalpine Grassland"], [8104, "Utility Swath - Herbaceous"], [7319, "West Gulf Coastal Plain Northern Calcareous Prairie"], [7320, "West Gulf Coastal Plain Southern Calcareous Prairie"], [7308, "Western Great Plains Foothill and Piedmont Grassland"], [7309, "Western Great Plains Sand Prairie"], [7310, "Western Great Plains Shortgrass Prairie"], [7311, "Western Great Plains Tallgrass Prairie"]], "SpeciesCode": "bYHBLx", "intIntoBuffWV": null, "cbxContPatch": false, "SubspeciesName": "", "intFromBuffFW": null, "memHandModelNotes": null, "intElevMin": 105, "ysnHydroOW": false, "Region": "Great Plains", "CommonName": "Yellow-headed Blackbird", "ysnUrbanInclude": false, "strUseForInt": null, "intEdgeEcoWidth": null, "intFromBuffWV": null, "strStreamVel": null, "Modeler": "", "strEdgeType": null, "strSalinity": null, "ysnHydroFW": false, "Reviewer": "", "ysnUrbanExclude": false, "strAvoid": null, "intFromBuffOW": null}}, "references": {"R81GAR01USGP": "Garrett, K. and J. Dunn. 1981. Birds of southern California: status and distribution. Los Angeles Audubon Soc. Los Angeles, CA.", "B90ZEI03NAUS": "Zeiner, D. C., W. F. Laudenslayer Jr., and K. E. Mayer (editors). 1990. California's Wildlife. Vol. 2. Birds. California Statewide Wildlife Habitat Relat. System, California. Resources Agency, Dept. Fish and Game, Sacramento, California.", "W95TWE01USGP": "Twedt, Daniel J. and Richard D. Crawford. 1995. Yellow-headed Blackbird (Xanthocephalus xanthocephalus), The Birds of North America Online (A. Poole, Ed.). Ithaca: Cornell Lab of Ornithology; Retrieved from the Birds of North America Online: http://bna.birds.cornell.edu/bna/species/192."}, "habitat_description": null, "taxonomic": {"gap_code": "bYHBLx", "ELCode": "ABPBXB3010", "scientific_name": "Xanthocephalus xanthocephalus", "ITIS_TSN": "179043", "Global_SEQ_ID": "106463", "common_name": "Yellow-headed Blackbird"}}